echoswift/__init__.py
echoswift/cli.py
echoswift/dataset.py
echoswift/llm_inference_benchmark.py
echoswift/llm_inference_master.py
echoswift/optimaluser.py
echoswift/utils/avg_locust_results.py
echoswift/utils/plot_results.py
echoswift-2.0.2.dist-info/LICENSE
echoswift-2.0.2.dist-info/METADATA
echoswift-2.0.2.dist-info/WHEEL
echoswift-2.0.2.dist-info/entry_points.txt
echoswift-2.0.2.dist-info/top_level.txt
echoswift-2.0.2.dist-info/RECORD
