Metadata-Version: 2.1
Name: echoswift
Version: 2.0.2
Summary: LLM Inference Benchmarking Tool
Home-page: https://github.com/Infobellit-Solutions-Pvt-Ltd/EchoSwift
Author: Infobell AI Team
Author-email: sarthak@infobellit.com
Classifier: Programming Language :: Python :: 3
Classifier: License :: OSI Approved :: MIT License
Classifier: Operating System :: OS Independent
Requires-Python: >=3.10
License-File: LICENSE
Requires-Dist: click
Requires-Dist: pyyaml
Requires-Dist: tqdm
Requires-Dist: pandas
Requires-Dist: matplotlib
Requires-Dist: locust
Requires-Dist: transformers
Requires-Dist: datasets
Requires-Dist: tabulate
Requires-Dist: keyboard
